setup.py
pygelf/__init__.py
pygelf/gelf.py
pygelf/handlers.py
pygelf_ex-0.0.3.dist-info/METADATA
pygelf_ex-0.0.3.dist-info/WHEEL
pygelf_ex-0.0.3.dist-info/licenses/LICENSE
pygelf_ex-0.0.3.dist-info/RECORD
