Metadata-Version: 2.1
Name: pygelf-ex
Version: 0.0.3
Summary: Logging handlers with GELF support
Project-URL: Homepage, https://github.com/rs-anders-agren/pygelf-ex
Author-email: Ivan Mukhin <muhin.ivan@gmail.com>, Anders Ågren <anders.agren@rssoftware.se>
License-File: LICENSE
Classifier: License :: OSI Approved :: MIT License
Classifier: Operating System :: OS Independent
Classifier: Programming Language :: Python :: 3
Requires-Python: >=3.7
